akashmodone/__init__.py
akashmodone/pythonmath.py
akshmodeone-0.2.0.dist-info/METADATA
akshmodeone-0.2.0.dist-info/WHEEL
akshmodeone-0.2.0.dist-info/top_level.txt
akshmodeone-0.2.0.dist-info/RECORD
