Metadata-Version: 2.1
Name: akshmodeone
Version: 0.2.0
Summary: A samlpe python module
Author: akash c abhilash
Author-email: akash@gmail.com
Requires-Python: >=3.6
